faultmaplib/__init__.py
faultmaplib/_nbdev.py
faultmaplib/core.py
faultmaplib-0.0.1.dist-info/LICENSE
faultmaplib-0.0.1.dist-info/METADATA
faultmaplib-0.0.1.dist-info/WHEEL
faultmaplib-0.0.1.dist-info/entry_points.txt
faultmaplib-0.0.1.dist-info/top_level.txt
faultmaplib-0.0.1.dist-info/RECORD
